{"n_dim": 3, "n_trials": 340, "objective": "schwefel_on_cube", "white": "optuna_random_clone_1", "black": "scipy_nelder", "traceback": ["passing", "passing"], "best_val": [0.41133124001862176, 0.500000098264025], "best_x": [[0.7231471916343298, 0.5169705640283018, 0.9387378061687731], [0.3746405104440226, 0.37464051044402275, 0.3746405104440227]], "feval_count": [340, 69], "n_trials_instructed": [340, 340], "passing": [true, true], "completed": true, "points": 1.0, "winner": "optuna_random_clone_1", "loser": "scipy_nelder"}